{
    "total": [
        {
            "id": "100044582742531",
            "count": 0
        },
        {
            "id": "100047869565269",
            "count": 0
        },
        {
            "id": "100061109995498",
            "count": 2
        },
        {
            "id": "100068094188928",
            "count": 23
        },
        {
            "id": "100069656838252",
            "count": 0
        },
        {
            "id": "100071089217253",
            "count": 5
        },
        {
            "id": "100072473172501",
            "count": 7
        },
        {
            "id": "100074862624882",
            "count": 1
        },
        {
            "id": "100075301001884",
            "count": 0
        },
        {
            "id": "100075526309728",
            "count": 0
        },
        {
            "id": "100076822761504",
            "count": 0
        },
        {
            "id": "100077386097249",
            "count": 0
        },
        {
            "id": "100078541507721",
            "count": 0
        },
        {
            "id": "100078894464271",
            "count": 0
        },
        {
            "id": "100081980142227",
            "count": 0
        },
        {
            "id": "100083332896307",
            "count": 0
        },
        {
            "id": "100083688866839",
            "count": 0
        },
        {
            "id": "100086229229356",
            "count": 0
        }
    ],
    "week": [
        {
            "id": "100044582742531",
            "count": 0,
            "name": "Người dùng Facebook"
        },
        {
            "id": "100047869565269",
            "count": 0,
            "name": "Gia Huy"
        },
        {
            "id": "100061109995498",
            "count": 0,
            "name": "Anhh Ngoc"
        },
        {
            "id": "100068094188928",
            "count": 0,
            "name": "Hoàng Thị Thúy Vân"
        },
        {
            "id": "100069656838252",
            "count": 0,
            "name": "Thuu Hiền"
        },
        {
            "id": "100071089217253",
            "count": 0,
            "name": "Ebe Anh"
        },
        {
            "id": "100072473172501",
            "count": 0,
            "name": "Minh Hiếu"
        },
        {
            "id": "100074862624882",
            "count": 0,
            "name": "San Họ Nguyễn"
        },
        {
            "id": "100075301001884",
            "count": 0,
            "name": "Nguyễn Nam"
        },
        {
            "id": "100075526309728",
            "count": 0,
            "name": "Trần Uyên"
        },
        {
            "id": "100076822761504",
            "count": 0,
            "name": "Nguyễn Thùy Linh"
        },
        {
            "id": "100077386097249",
            "count": 0,
            "name": "Thị Yến"
        },
        {
            "id": "100078541507721",
            "count": 0,
            "name": "Quynh Ank"
        },
        {
            "id": "100078894464271",
            "count": 0,
            "name": "Ngọc Ánh"
        },
        {
            "id": "100081980142227",
            "count": 0,
            "name": "Thanh Quý"
        },
        {
            "id": "100083332896307",
            "count": 0,
            "name": "Ebe Giang"
        },
        {
            "id": "100083688866839",
            "count": 0,
            "name": "Minh Thuy"
        },
        {
            "id": "100086229229356",
            "count": 0,
            "name": "Ka Nờ"
        }
    ],
    "day": [
        {
            "id": "100044582742531",
            "count": 0,
            "name": "Người dùng Facebook"
        },
        {
            "id": "100047869565269",
            "count": 0,
            "name": "Gia Huy"
        },
        {
            "id": "100061109995498",
            "count": 0,
            "name": "Anhh Ngoc"
        },
        {
            "id": "100068094188928",
            "count": 0,
            "name": "Hoàng Thị Thúy Vân"
        },
        {
            "id": "100069656838252",
            "count": 0,
            "name": "Thuu Hiền"
        },
        {
            "id": "100071089217253",
            "count": 0,
            "name": "Ebe Anh"
        },
        {
            "id": "100072473172501",
            "count": 0,
            "name": "Minh Hiếu"
        },
        {
            "id": "100074862624882",
            "count": 0,
            "name": "San Họ Nguyễn"
        },
        {
            "id": "100075301001884",
            "count": 0,
            "name": "Nguyễn Nam"
        },
        {
            "id": "100075526309728",
            "count": 0,
            "name": "Trần Uyên"
        },
        {
            "id": "100076822761504",
            "count": 0,
            "name": "Nguyễn Thùy Linh"
        },
        {
            "id": "100077386097249",
            "count": 0,
            "name": "Thị Yến"
        },
        {
            "id": "100078541507721",
            "count": 0,
            "name": "Quynh Ank"
        },
        {
            "id": "100078894464271",
            "count": 0,
            "name": "Ngọc Ánh"
        },
        {
            "id": "100081980142227",
            "count": 0,
            "name": "Thanh Quý"
        },
        {
            "id": "100083332896307",
            "count": 0,
            "name": "Ebe Giang"
        },
        {
            "id": "100083688866839",
            "count": 0,
            "name": "Minh Thuy"
        },
        {
            "id": "100086229229356",
            "count": 0,
            "name": "Ka Nờ"
        }
    ],
    "time": 6
}