{
    "total": [
        {
            "id": "100013683156756",
            "count": 0
        },
        {
            "id": "100025376343713",
            "count": 21
        },
        {
            "id": "100028101636970",
            "count": 0
        },
        {
            "id": "100029201589418",
            "count": 0
        },
        {
            "id": "100030384772708",
            "count": 0
        },
        {
            "id": "100044250260076",
            "count": 4
        },
        {
            "id": "100052175355729",
            "count": 0
        },
        {
            "id": "100054387787269",
            "count": 13
        },
        {
            "id": "100061190685966",
            "count": 2
        },
        {
            "id": "100065345653149",
            "count": 1
        },
        {
            "id": "100068094188928",
            "count": 137
        },
        {
            "id": "100073676385398",
            "count": 28
        },
        {
            "id": "100074404707176",
            "count": 0
        },
        {
            "id": "100075547376765",
            "count": 43
        },
        {
            "id": "100076378925146",
            "count": 17
        },
        {
            "id": "100076476152674",
            "count": 0
        },
        {
            "id": "100078373411608",
            "count": 0
        },
        {
            "id": "100080512383581",
            "count": 11
        },
        {
            "id": "100082583737788",
            "count": 0
        },
        {
            "id": "100083781472153",
            "count": 0
        },
        {
            "id": "100084991121214",
            "count": 4
        },
        {
            "id": "100085449447248",
            "count": 0
        },
        {
            "id": "100086032068092",
            "count": 0
        },
        {
            "id": "100087069468136",
            "count": 72
        },
        {
            "id": "100087347727287",
            "count": 25
        },
        {
            "id": "100087363092098",
            "count": 1
        },
        {
            "id": "100087930536868",
            "count": 2
        },
        {
            "id": "100074690914260",
            "count": 16
        },
        {
            "id": "100058094425739",
            "count": 4
        },
        {
            "id": "100055031580637",
            "count": 41
        },
        {
            "id": "100085574700273",
            "count": 40
        },
        {
            "id": "100081861462720",
            "count": 3
        },
        {
            "id": "100087438951039",
            "count": 6
        },
        {
            "id": "100049497623815",
            "count": 1
        },
        {
            "id": "100056578389970",
            "count": 19
        }
    ],
    "week": [
        {
            "id": "100013683156756",
            "count": 0,
            "name": "Hoàng Thắng"
        },
        {
            "id": "100025376343713",
            "count": 0,
            "name": "Nguyễn Ngọc Cảnh"
        },
        {
            "id": "100028101636970",
            "count": 0,
            "name": "Lộc Anh Dân"
        },
        {
            "id": "100029201589418",
            "count": 0,
            "name": "Hoàng Phúc"
        },
        {
            "id": "100030384772708",
            "count": 0,
            "name": "Le Hai Yen"
        },
        {
            "id": "100044250260076",
            "count": 0,
            "name": "Nguoi Yeu"
        },
        {
            "id": "100052175355729",
            "count": 0,
            "name": "Văn Hiếu Thái"
        },
        {
            "id": "100054387787269",
            "count": 0,
            "name": "Quang Phước"
        },
        {
            "id": "100061190685966",
            "count": 0,
            "name": "Thuy Linh"
        },
        {
            "id": "100065345653149",
            "count": 0,
            "name": "Trần Mạnh Hoàng"
        },
        {
            "id": "100068094188928",
            "count": 0,
            "name": "Hoàng Thị Thúy Vân"
        },
        {
            "id": "100073676385398",
            "count": 0,
            "name": "T. Huyền"
        },
        {
            "id": "100074404707176",
            "count": 0,
            "name": "Kiều Hà"
        },
        {
            "id": "100075547376765",
            "count": 0,
            "name": "Thiên Ân"
        },
        {
            "id": "100076378925146",
            "count": 0,
            "name": "Nguyễn Tú"
        },
        {
            "id": "100076476152674",
            "count": 0,
            "name": "Duy Bằng"
        },
        {
            "id": "100078373411608",
            "count": 0,
            "name": "La Van Huy"
        },
        {
            "id": "100080512383581",
            "count": 0,
            "name": "Heo Võ"
        },
        {
            "id": "100082583737788",
            "count": 0,
            "name": "Dat Vu Van"
        },
        {
            "id": "100083781472153",
            "count": 0,
            "name": "Sovereign Đinh"
        },
        {
            "id": "100084991121214",
            "count": 0,
            "name": "Đàm Tuấn"
        },
        {
            "id": "100085449447248",
            "count": 0,
            "name": "Yến Nhi"
        },
        {
            "id": "100086032068092",
            "count": 0,
            "name": "Hoàng Sơn"
        },
        {
            "id": "100087069468136",
            "count": 0,
            "name": "Gấu Bae"
        },
        {
            "id": "100087347727287",
            "count": 0,
            "name": "Quang Vinh"
        },
        {
            "id": "100087363092098",
            "count": 0,
            "name": "Hải Hải"
        },
        {
            "id": "100087930536868",
            "count": 0,
            "name": "Trần Vinh"
        },
        {
            "id": "100074690914260",
            "count": 0,
            "name": "Nguyễn Minh Tùng"
        },
        {
            "id": "100058094425739",
            "count": 0,
            "name": "Đức Phạm"
        },
        {
            "id": "100055031580637",
            "count": 0,
            "name": "Bùi Đức Thắng"
        },
        {
            "id": "100085574700273",
            "count": 0,
            "name": "Nguyễn Thanh"
        },
        {
            "id": "100081861462720",
            "count": 0,
            "name": "Nguyễn Minh Nhã"
        },
        {
            "id": "100087438951039",
            "count": 0,
            "name": "Phùng Tuấn Hải"
        },
        {
            "id": "100049497623815",
            "count": 0,
            "name": "Thanh Tùng"
        },
        {
            "id": "100056578389970",
            "count": 0,
            "name": "Trần Mạnh Quỳnh"
        }
    ],
    "day": [
        {
            "id": "100013683156756",
            "count": 0,
            "name": "Hoàng Thắng"
        },
        {
            "id": "100025376343713",
            "count": 0,
            "name": "Nguyễn Ngọc Cảnh"
        },
        {
            "id": "100028101636970",
            "count": 0,
            "name": "Lộc Anh Dân"
        },
        {
            "id": "100029201589418",
            "count": 0,
            "name": "Hoàng Phúc"
        },
        {
            "id": "100030384772708",
            "count": 0,
            "name": "Le Hai Yen"
        },
        {
            "id": "100044250260076",
            "count": 0,
            "name": "Nguoi Yeu"
        },
        {
            "id": "100052175355729",
            "count": 0,
            "name": "Văn Hiếu Thái"
        },
        {
            "id": "100054387787269",
            "count": 0,
            "name": "Quang Phước"
        },
        {
            "id": "100061190685966",
            "count": 0,
            "name": "Thuy Linh"
        },
        {
            "id": "100065345653149",
            "count": 0,
            "name": "Trần Mạnh Hoàng"
        },
        {
            "id": "100068094188928",
            "count": 0,
            "name": "Hoàng Thị Thúy Vân"
        },
        {
            "id": "100073676385398",
            "count": 0,
            "name": "T. Huyền"
        },
        {
            "id": "100074404707176",
            "count": 0,
            "name": "Kiều Hà"
        },
        {
            "id": "100075547376765",
            "count": 0,
            "name": "Thiên Ân"
        },
        {
            "id": "100076378925146",
            "count": 0,
            "name": "Nguyễn Tú"
        },
        {
            "id": "100076476152674",
            "count": 0,
            "name": "Duy Bằng"
        },
        {
            "id": "100078373411608",
            "count": 0,
            "name": "La Van Huy"
        },
        {
            "id": "100080512383581",
            "count": 0,
            "name": "Heo Võ"
        },
        {
            "id": "100082583737788",
            "count": 0,
            "name": "Dat Vu Van"
        },
        {
            "id": "100083781472153",
            "count": 0,
            "name": "Sovereign Đinh"
        },
        {
            "id": "100084991121214",
            "count": 0,
            "name": "Đàm Tuấn"
        },
        {
            "id": "100085449447248",
            "count": 0,
            "name": "Yến Nhi"
        },
        {
            "id": "100086032068092",
            "count": 0,
            "name": "Hoàng Sơn"
        },
        {
            "id": "100087069468136",
            "count": 0,
            "name": "Gấu Bae"
        },
        {
            "id": "100087347727287",
            "count": 0,
            "name": "Quang Vinh"
        },
        {
            "id": "100087363092098",
            "count": 0,
            "name": "Hải Hải"
        },
        {
            "id": "100087930536868",
            "count": 0,
            "name": "Trần Vinh"
        },
        {
            "id": "100074690914260",
            "count": 0,
            "name": "Nguyễn Minh Tùng"
        },
        {
            "id": "100058094425739",
            "count": 0,
            "name": "Đức Phạm"
        },
        {
            "id": "100055031580637",
            "count": 0,
            "name": "Bùi Đức Thắng"
        },
        {
            "id": "100085574700273",
            "count": 0,
            "name": "Nguyễn Thanh"
        },
        {
            "id": "100081861462720",
            "count": 0,
            "name": "Nguyễn Minh Nhã"
        },
        {
            "id": "100087438951039",
            "count": 0,
            "name": "Phùng Tuấn Hải"
        },
        {
            "id": "100049497623815",
            "count": 0,
            "name": "Thanh Tùng"
        },
        {
            "id": "100056578389970",
            "count": 0,
            "name": "Trần Mạnh Quỳnh"
        }
    ],
    "time": 6
}