{
    "total": [
        {
            "id": "100087438951039",
            "count": 52
        },
        {
            "id": "100084003383533",
            "count": 1
        },
        {
            "id": "100086909598574",
            "count": 5
        },
        {
            "id": "100076506731308",
            "count": 4
        },
        {
            "id": "100076222216500",
            "count": 1
        },
        {
            "id": "100045968490951",
            "count": 2
        },
        {
            "id": "100080775557141",
            "count": 3
        },
        {
            "id": "100086759273930",
            "count": 8
        },
        {
            "id": "100076119867786",
            "count": 14
        },
        {
            "id": "100017718375203",
            "count": 5
        },
        {
            "id": "100057113530472",
            "count": 1
        },
        {
            "id": "100070367513055",
            "count": 2
        }
    ],
    "week": [
        {
            "id": "100087438951039",
            "count": 0,
            "name": "Phùng Tuấn Hải"
        },
        {
            "id": "100084003383533",
            "count": 0,
            "name": "Trịnh Thương Thương"
        },
        {
            "id": "100086909598574",
            "count": 0,
            "name": "Lủng Thít Socola"
        },
        {
            "id": "100076506731308",
            "count": 0,
            "name": "Ng Linq"
        },
        {
            "id": "100076222216500",
            "count": 0,
            "name": "Ngyen Khôy"
        },
        {
            "id": "100045968490951",
            "count": 0,
            "name": "Nguyễn Trân"
        },
        {
            "id": "100080775557141",
            "count": 0,
            "name": "Huyền Trân"
        },
        {
            "id": "100086759273930",
            "count": 0,
            "name": "Nguyễn Ngân"
        },
        {
            "id": "100076119867786",
            "count": 0,
            "name": "Nguyn Phuong Giangg"
        },
        {
            "id": "100017718375203",
            "count": 0,
            "name": "Trần Thiện"
        },
        {
            "id": "100057113530472",
            "count": 0,
            "name": "Thảo Nguyên"
        },
        {
            "id": "100070367513055",
            "count": 0,
            "name": "Ng Thi Yen Nhi"
        }
    ],
    "day": [
        {
            "id": "100087438951039",
            "count": 0,
            "name": "Phùng Tuấn Hải"
        },
        {
            "id": "100084003383533",
            "count": 0,
            "name": "Trịnh Thương Thương"
        },
        {
            "id": "100086909598574",
            "count": 0,
            "name": "Lủng Thít Socola"
        },
        {
            "id": "100076506731308",
            "count": 0,
            "name": "Ng Linq"
        },
        {
            "id": "100076222216500",
            "count": 0,
            "name": "Ngyen Khôy"
        },
        {
            "id": "100045968490951",
            "count": 0,
            "name": "Nguyễn Trân"
        },
        {
            "id": "100080775557141",
            "count": 0,
            "name": "Huyền Trân"
        },
        {
            "id": "100086759273930",
            "count": 0,
            "name": "Nguyễn Ngân"
        },
        {
            "id": "100076119867786",
            "count": 0,
            "name": "Nguyn Phuong Giangg"
        },
        {
            "id": "100017718375203",
            "count": 0,
            "name": "Trần Thiện"
        },
        {
            "id": "100057113530472",
            "count": 0,
            "name": "Thảo Nguyên"
        },
        {
            "id": "100070367513055",
            "count": 0,
            "name": "Ng Thi Yen Nhi"
        }
    ],
    "time": 6
}